[[0.072086,{"lines":{"0":[["ikhsan@M5-X:/etc/apt/sources.list.d$                                                                         ",{}]],"1":[["                                                                                                             ",{}]],"2":[["                                                                                                             ",{}]],"3":[["                                                                                                             ",{}]],"4":[["                                                                                                             ",{}]],"5":[["                                                                                                             ",{}]],"6":[["                                                                                                             ",{}]],"7":[["                                                                                                             ",{}]],"8":[["                                                                                                             ",{}]],"9":[["                                                                                                             ",{}]],"10":[["                                                                                                             ",{}]],"11":[["                                                                                                             ",{}]],"12":[["                                                                                                             ",{}]],"13":[["                                                                                                             ",{}]],"14":[["                                                                                                             ",{}]],"15":[["                                                                                                             ",{}]],"16":[["                                                                                                             ",{}]],"17":[["                                                                                                             ",{}]],"18":[["                                                                                                             ",{}]],"19":[["                                                                                                             ",{}]],"20":[["                                                                                                             ",{}]],"21":[["                                                                                                             ",{}]],"22":[["                                                                                                             ",{}]],"23":[["                                                                                                             ",{}]],"24":[["                                                                                                             ",{}]],"25":[["                                                                                                             ",{}]],"26":[["                                                                                                             ",{}]]},"cursor":{"x":37,"y":0,"visible":true}}],[1.926556,{"lines":{"0":[["ikhsan@M5-X:/etc/apt/sources.list.d$ c                                                                       ",{}]]},"cursor":{"x":38}}],[0.084074,{"lines":{"0":[["ikhsan@M5-X:/etc/apt/sources.list.d$ cd                                                                      ",{}]]},"cursor":{"x":39}}],[0.183925,{"cursor":{"x":40}}],[0.592825,{"lines":{"0":[["ikhsan@M5-X:/etc/apt/sources.list.d$ cd /                                                                    ",{}]]},"cursor":{"x":41}}],[1.867175,{"lines":{"0":[["ikhsan@M5-X:/etc/apt/sources.list.d$ cd /v                                                                   ",{}]]},"cursor":{"x":42}}],[0.280734,{"lines":{"0":[["ikhsan@M5-X:/etc/apt/sources.list.d$ cd /va                                                                  ",{}]]},"cursor":{"x":43}}],[0.26009,{"lines":{"0":[["ikhsan@M5-X:/etc/apt/sources.list.d$ cd /var                                                                 ",{}]]},"cursor":{"x":44}}],[0.339379,{"lines":{"1":[["ikhsan@M5-X:/var$                                                                                            ",{}]]},"cursor":{"x":18,"y":1}}],[0.7838619999999999,{"lines":{"1":[["ikhsan@M5-X:/var$ s                                                                                          ",{}]]},"cursor":{"x":19}}],[0.23979,{"lines":{"1":[["ikhsan@M5-X:/var$ su                                                                                         ",{}]]},"cursor":{"x":20}}],[0.163277,{"lines":{"1":[["ikhsan@M5-X:/var$ sud                                                                                        ",{}]]},"cursor":{"x":21}}],[0.200987,{"lines":{"1":[["ikhsan@M5-X:/var$ sudo                                                                                       ",{}]]},"cursor":{"x":22}}],[0.5309739999999999,{"cursor":{"x":23}}],[0.679949,{"lines":{"1":[["ikhsan@M5-X:/var$ sudo d                                                                                     ",{}]]},"cursor":{"x":24}}],[0.251924,{"lines":{"1":[["ikhsan@M5-X:/var$ sudo du                                                                                    ",{}]]},"cursor":{"x":25}}],[0.16409,{"cursor":{"x":26}}],[0.2647,{"lines":{"1":[["ikhsan@M5-X:/var$ sudo du -                                                                                  ",{}]]},"cursor":{"x":27}}],[0.203175,{"lines":{"1":[["ikhsan@M5-X:/var$ sudo du -s                                                                                 ",{}]]},"cursor":{"x":28}}],[0.196521,{"lines":{"1":[["ikhsan@M5-X:/var$ sudo du -sh                                                                                ",{}]]},"cursor":{"x":29}}],[0.187587,{"cursor":{"x":30}}],[0.380604,{"lines":{"1":[["ikhsan@M5-X:/var$ sudo du -sh *                                                                              ",{}]]},"cursor":{"x":31}}],[0.529095,{"cursor":{"x":0,"y":2}}],[0.032268,{"lines":{"2":[["[sudo] password for ikhsan:                                                                                  ",{}]]},"cursor":{"x":28}}],[2.513493,{"cursor":{"x":0,"y":3}}],[0.004007,{"lines":{"3":[["6,7M    backups                                                                                              ",{}]]},"cursor":{"y":4}}],[0.107702,{"lines":{"4":[["605M    cache                                                                                                ",{}]]},"cursor":{"y":5}}],[2.3e-05,{"lines":{"5":[["33M     crash                                                                                                ",{}]]},"cursor":{"y":6}}],[0.307145,{"lines":{"6":[["350M    lib                                                                                                  ",{}]]},"cursor":{"y":7}}],[0.01461,{"lines":{"7":[["4,0K    local                                                                                                ",{}]],"8":[["0       lock                                                                                                 ",{}]],"9":[["12M     log                                                                                                  ",{}]],"10":[["4,0K    mail                                                                                                 ",{}]],"11":[["4,0K    metrics                                                                                              ",{}]],"12":[["4,0K    opt                                                                                                  ",{}]],"13":[["0       run                                                                                                  ",{}]],"14":[["64K     spool                                                                                                ",{}]],"15":[["11M     tmp                                                                                                  ",{}]],"16":[["ikhsan@M5-X:/var$                                                                                            ",{}]]},"cursor":{"x":18,"y":16}}],[5.091479,{"lines":{"16":[["ikhsan@M5-X:/var$ c                                                                                          ",{}]]},"cursor":{"x":19}}],[0.103498,{"lines":{"16":[["ikhsan@M5-X:/var$ cd                                                                                         ",{}]]},"cursor":{"x":20}}],[0.172194,{"cursor":{"x":21}}],[0.319858,{"lines":{"16":[["ikhsan@M5-X:/var$ cd /                                                                                       ",{}]]},"cursor":{"x":22}}],[0.328187,{"lines":{"17":[["ikhsan@M5-X:/$                                                                                               ",{}]]},"cursor":{"x":15,"y":17}}],[0.8078880000000001,{"lines":{"17":[["ikhsan@M5-X:/$ s                                                                                             ",{}]]},"cursor":{"x":16}}],[0.160767,{"lines":{"17":[["ikhsan@M5-X:/$ su                                                                                            ",{}]]},"cursor":{"x":17}}],[0.16729,{"lines":{"17":[["ikhsan@M5-X:/$ sud                                                                                           ",{}]]},"cursor":{"x":18}}],[0.155987,{"lines":{"17":[["ikhsan@M5-X:/$ sudo                                                                                          ",{}]]},"cursor":{"x":19}}],[0.5719610000000001,{"cursor":{"x":20}}],[0.499931,{"lines":{"17":[["ikhsan@M5-X:/$ sudo s                                                                                        ",{}]]},"cursor":{"x":21}}],[1.523906,{"lines":{"17":[["ikhsan@M5-X:/$ sudo                                                                                          ",{}]]},"cursor":{"x":20}}],[0.560968,{"lines":{"17":[["ikhsan@M5-X:/$ sudo d                                                                                        ",{}]]},"cursor":{"x":21}}],[0.139837,{"lines":{"17":[["ikhsan@M5-X:/$ sudo du                                                                                       ",{}]]},"cursor":{"x":22}}],[0.172066,{"cursor":{"x":23}}],[0.331245,{"lines":{"17":[["ikhsan@M5-X:/$ sudo du -                                                                                     ",{}]]},"cursor":{"x":24}}],[1.200618,{"lines":{"17":[["ikhsan@M5-X:/$ sudo du -s                                                                                    ",{}]]},"cursor":{"x":25}}],[0.119256,{"lines":{"17":[["ikhsan@M5-X:/$ sudo du -sh                                                                                   ",{}]]},"cursor":{"x":26}}],[0.43218,{"cursor":{"x":27}}],[0.460749,{"lines":{"17":[["ikhsan@M5-X:/$ sudo du -sh *                                                                                 ",{}]]},"cursor":{"x":28}}],[0.360689,{"cursor":{"x":0,"y":18}}],[0.031996,{"lines":{"18":[["8,0K    backupscript                                                                                         ",{}]],"19":[["9,7M    bin                                                                                                  ",{}]]},"cursor":{"y":20}}],[0.044047,{"lines":{"20":[["133M    boot                                                                                                 ",{}]]},"cursor":{"y":21}}],[0.021506,{"lines":{"21":[["4,0K    cdrom                                                                                                ",{}]],"22":[["4,0K    dev                                                                                                  ",{}]]},"cursor":{"y":23}}],[0.432611,{"lines":{"23":[["52M     etc                                                                                                  ",{}]]},"cursor":{"y":24}}],[7.42978,{"lines":{"24":[["160G    home                                                                                                 ",{}]]},"cursor":{"y":25}}],[0.019688,{"lines":{"0":[["ikhsan@M5-X:/var$ sudo du -sh *                                                                              ",{}]],"1":[["[sudo] password for ikhsan:                                                                                  ",{}]],"2":[["6,7M    backups                                                                                              ",{}]],"3":[["605M    cache                                                                                                ",{}]],"4":[["33M     crash                                                                                                ",{}]],"5":[["350M    lib                                                                                                  ",{}]],"6":[["4,0K    local                                                                                                ",{}]],"7":[["0       lock                                                                                                 ",{}]],"8":[["12M     log                                                                                                  ",{}]],"9":[["4,0K    mail                                                                                                 ",{}]],"10":[["4,0K    metrics                                                                                              ",{}]],"11":[["4,0K    opt                                                                                                  ",{}]],"12":[["0       run                                                                                                  ",{}]],"13":[["64K     spool                                                                                                ",{}]],"14":[["11M     tmp                                                                                                  ",{}]],"15":[["ikhsan@M5-X:/var$ cd /                                                                                       ",{}]],"16":[["ikhsan@M5-X:/$ sudo du -sh *                                                                                 ",{}]],"17":[["8,0K    backupscript                                                                                         ",{}]],"18":[["9,7M    bin                                                                                                  ",{}]],"19":[["133M    boot                                                                                                 ",{}]],"20":[["4,0K    cdrom                                                                                                ",{}]],"21":[["4,0K    dev                                                                                                  ",{}]],"22":[["52M     etc                                                                                                  ",{}]],"23":[["160G    home                                                                                                 ",{}]],"24":[["0       initrd.img                                                                                           ",{}]],"25":[["0       initrd.img.old                                                                                       ",{}]]},"cursor":{"y":26}}],[2.484671,{"lines":{"0":[["[sudo] password for ikhsan:                                                                                  ",{}]],"1":[["6,7M    backups                                                                                              ",{}]],"2":[["605M    cache                                                                                                ",{}]],"3":[["33M     crash                                                                                                ",{}]],"4":[["350M    lib                                                                                                  ",{}]],"5":[["4,0K    local                                                                                                ",{}]],"6":[["0       lock                                                                                                 ",{}]],"7":[["12M     log                                                                                                  ",{}]],"8":[["4,0K    mail                                                                                                 ",{}]],"9":[["4,0K    metrics                                                                                              ",{}]],"10":[["4,0K    opt                                                                                                  ",{}]],"11":[["0       run                                                                                                  ",{}]],"12":[["64K     spool                                                                                                ",{}]],"13":[["11M     tmp                                                                                                  ",{}]],"14":[["ikhsan@M5-X:/var$ cd /                                                                                       ",{}]],"15":[["ikhsan@M5-X:/$ sudo du -sh *                                                                                 ",{}]],"16":[["8,0K    backupscript                                                                                         ",{}]],"17":[["9,7M    bin                                                                                                  ",{}]],"18":[["133M    boot                                                                                                 ",{}]],"19":[["4,0K    cdrom                                                                                                ",{}]],"20":[["4,0K    dev                                                                                                  ",{}]],"21":[["52M     etc                                                                                                  ",{}]],"22":[["160G    home                                                                                                 ",{}]],"23":[["0       initrd.img                                                                                           ",{}]],"24":[["0       initrd.img.old                                                                                       ",{}]],"25":[["671M    lib                                                                                                  ",{}]]}}],[0.022742,{"lines":{"0":[["6,7M    backups                                                                                              ",{}]],"1":[["605M    cache                                                                                                ",{}]],"2":[["33M     crash                                                                                                ",{}]],"3":[["350M    lib                                                                                                  ",{}]],"4":[["4,0K    local                                                                                                ",{}]],"5":[["0       lock                                                                                                 ",{}]],"6":[["12M     log                                                                                                  ",{}]],"7":[["4,0K    mail                                                                                                 ",{}]],"8":[["4,0K    metrics                                                                                              ",{}]],"9":[["4,0K    opt                                                                                                  ",{}]],"10":[["0       run                                                                                                  ",{}]],"11":[["64K     spool                                                                                                ",{}]],"12":[["11M     tmp                                                                                                  ",{}]],"13":[["ikhsan@M5-X:/var$ cd /                                                                                       ",{}]],"14":[["ikhsan@M5-X:/$ sudo du -sh *                                                                                 ",{}]],"15":[["8,0K    backupscript                                                                                         ",{}]],"16":[["9,7M    bin                                                                                                  ",{}]],"17":[["133M    boot                                                                                                 ",{}]],"18":[["4,0K    cdrom                                                                                                ",{}]],"19":[["4,0K    dev                                                                                                  ",{}]],"20":[["52M     etc                                                                                                  ",{}]],"21":[["160G    home                                                                                                 ",{}]],"22":[["0       initrd.img                                                                                           ",{}]],"23":[["0       initrd.img.old                                                                                       ",{}]],"24":[["671M    lib                                                                                                  ",{}]],"25":[["3,5M    lib32                                                                                                ",{}]]}}],[0.01638,{"lines":{"0":[["350M    lib                                                                                                  ",{}]],"1":[["4,0K    local                                                                                                ",{}]],"2":[["0       lock                                                                                                 ",{}]],"3":[["12M     log                                                                                                  ",{}]],"4":[["4,0K    mail                                                                                                 ",{}]],"5":[["4,0K    metrics                                                                                              ",{}]],"6":[["4,0K    opt                                                                                                  ",{}]],"7":[["0       run                                                                                                  ",{}]],"8":[["64K     spool                                                                                                ",{}]],"9":[["11M     tmp                                                                                                  ",{}]],"10":[["ikhsan@M5-X:/var$ cd /                                                                                       ",{}]],"11":[["ikhsan@M5-X:/$ sudo du -sh *                                                                                 ",{}]],"12":[["8,0K    backupscript                                                                                         ",{}]],"13":[["9,7M    bin                                                                                                  ",{}]],"14":[["133M    boot                                                                                                 ",{}]],"15":[["4,0K    cdrom                                                                                                ",{}]],"16":[["4,0K    dev                                                                                                  ",{}]],"17":[["52M     etc                                                                                                  ",{}]],"18":[["160G    home                                                                                                 ",{}]],"19":[["0       initrd.img                                                                                           ",{}]],"20":[["0       initrd.img.old                                                                                       ",{}]],"21":[["671M    lib                                                                                                  ",{}]],"22":[["3,5M    lib32                                                                                                ",{}]],"23":[["4,0K    lib64                                                                                                ",{}]],"24":[["16K     lost+found                                                                                           ",{}]],"25":[["8,0K    media                                                                                                ",{}]]}}],[0.014721,{"lines":{"0":[["4,0K    local                                                                                                ",{}]],"1":[["0       lock                                                                                                 ",{}]],"2":[["12M     log                                                                                                  ",{}]],"3":[["4,0K    mail                                                                                                 ",{}]],"4":[["4,0K    metrics                                                                                              ",{}]],"5":[["4,0K    opt                                                                                                  ",{}]],"6":[["0       run                                                                                                  ",{}]],"7":[["64K     spool                                                                                                ",{}]],"8":[["11M     tmp                                                                                                  ",{}]],"9":[["ikhsan@M5-X:/var$ cd /                                                                                       ",{}]],"10":[["ikhsan@M5-X:/$ sudo du -sh *                                                                                 ",{}]],"11":[["8,0K    backupscript                                                                                         ",{}]],"12":[["9,7M    bin                                                                                                  ",{}]],"13":[["133M    boot                                                                                                 ",{}]],"14":[["4,0K    cdrom                                                                                                ",{}]],"15":[["4,0K    dev                                                                                                  ",{}]],"16":[["52M     etc                                                                                                  ",{}]],"17":[["160G    home                                                                                                 ",{}]],"18":[["0       initrd.img                                                                                           ",{}]],"19":[["0       initrd.img.old                                                                                       ",{}]],"20":[["671M    lib                                                                                                  ",{}]],"21":[["3,5M    lib32                                                                                                ",{}]],"22":[["4,0K    lib64                                                                                                ",{}]],"23":[["16K     lost+found                                                                                           ",{}]],"24":[["8,0K    media                                                                                                ",{}]],"25":[["4,0K    mnt                                                                                                  ",{}]]}}],[0.290488,{"lines":{"0":[["0       lock                                                                                                 ",{}]],"1":[["12M     log                                                                                                  ",{}]],"2":[["4,0K    mail                                                                                                 ",{}]],"3":[["4,0K    metrics                                                                                              ",{}]],"4":[["4,0K    opt                                                                                                  ",{}]],"5":[["0       run                                                                                                  ",{}]],"6":[["64K     spool                                                                                                ",{}]],"7":[["11M     tmp                                                                                                  ",{}]],"8":[["ikhsan@M5-X:/var$ cd /                                                                                       ",{}]],"9":[["ikhsan@M5-X:/$ sudo du -sh *                                                                                 ",{}]],"10":[["8,0K    backupscript                                                                                         ",{}]],"11":[["9,7M    bin                                                                                                  ",{}]],"12":[["133M    boot                                                                                                 ",{}]],"13":[["4,0K    cdrom                                                                                                ",{}]],"14":[["4,0K    dev                                                                                                  ",{}]],"15":[["52M     etc                                                                                                  ",{}]],"16":[["160G    home                                                                                                 ",{}]],"17":[["0       initrd.img                                                                                           ",{}]],"18":[["0       initrd.img.old                                                                                       ",{}]],"19":[["671M    lib                                                                                                  ",{}]],"20":[["3,5M    lib32                                                                                                ",{}]],"21":[["4,0K    lib64                                                                                                ",{}]],"22":[["16K     lost+found                                                                                           ",{}]],"23":[["8,0K    media                                                                                                ",{}]],"24":[["4,0K    mnt                                                                                                  ",{}]],"25":[["345M    opt                                                                                                  ",{}]]}}],[0.170526,{"lines":{"26":[["du: cannot access ‘proc/15799/task/15799/fd/4’                                                               ",{}]]},"cursor":{"x":46}}],[0.00166,{"lines":{"0":[["0       run                                                                                                  ",{}]],"1":[["64K     spool                                                                                                ",{}]],"2":[["11M     tmp                                                                                                  ",{}]],"3":[["ikhsan@M5-X:/var$ cd /                                                                                       ",{}]],"4":[["ikhsan@M5-X:/$ sudo du -sh *                                                                                 ",{}]],"5":[["8,0K    backupscript                                                                                         ",{}]],"6":[["9,7M    bin                                                                                                  ",{}]],"7":[["133M    boot                                                                                                 ",{}]],"8":[["4,0K    cdrom                                                                                                ",{}]],"9":[["4,0K    dev                                                                                                  ",{}]],"10":[["52M     etc                                                                                                  ",{}]],"11":[["160G    home                                                                                                 ",{}]],"12":[["0       initrd.img                                                                                           ",{}]],"13":[["0       initrd.img.old                                                                                       ",{}]],"14":[["671M    lib                                                                                                  ",{}]],"15":[["3,5M    lib32                                                                                                ",{}]],"16":[["4,0K    lib64                                                                                                ",{}]],"17":[["16K     lost+found                                                                                           ",{}]],"18":[["8,0K    media                                                                                                ",{}]],"19":[["4,0K    mnt                                                                                                  ",{}]],"20":[["345M    opt                                                                                                  ",{}]],"21":[["du: cannot access ‘proc/15799/task/15799/fd/4’: No such file or directory                                    ",{}]],"22":[["du: cannot access ‘proc/15799/task/15799/fdinfo/4’: No such file or directory                                ",{}]],"23":[["du: cannot access ‘proc/15799/fd/4’: No such file or directory                                               ",{}]],"24":[["du: cannot access ‘proc/15799/fdinfo/4’: No such file or directory                                           ",{}]],"25":[["0       proc                                                                                                 ",{}]],"26":[["                                                                                                             ",{}]]},"cursor":{"x":0}}],[0.039638,{"lines":{"0":[["ikhsan@M5-X:/$ sudo du -sh *                                                                                 ",{}]],"1":[["8,0K    backupscript                                                                                         ",{}]],"2":[["9,7M    bin                                                                                                  ",{}]],"3":[["133M    boot                                                                                                 ",{}]],"4":[["4,0K    cdrom                                                                                                ",{}]],"5":[["4,0K    dev                                                                                                  ",{}]],"6":[["52M     etc                                                                                                  ",{}]],"7":[["160G    home                                                                                                 ",{}]],"8":[["0       initrd.img                                                                                           ",{}]],"9":[["0       initrd.img.old                                                                                       ",{}]],"10":[["671M    lib                                                                                                  ",{}]],"11":[["3,5M    lib32                                                                                                ",{}]],"12":[["4,0K    lib64                                                                                                ",{}]],"13":[["16K     lost+found                                                                                           ",{}]],"14":[["8,0K    media                                                                                                ",{}]],"15":[["4,0K    mnt                                                                                                  ",{}]],"16":[["345M    opt                                                                                                  ",{}]],"17":[["du: cannot access ‘proc/15799/task/15799/fd/4’: No such file or directory                                    ",{}]],"18":[["du: cannot access ‘proc/15799/task/15799/fdinfo/4’: No such file or directory                                ",{}]],"19":[["du: cannot access ‘proc/15799/fd/4’: No such file or directory                                               ",{}]],"20":[["du: cannot access ‘proc/15799/fdinfo/4’: No such file or directory                                           ",{}]],"21":[["0       proc                                                                                                 ",{}]],"22":[["748K    root                                                                                                 ",{}]],"23":[["du: cannot access ‘run/user/1000/gvfs’: Permission denied                                                    ",{}]],"24":[["4,7M    run                                                                                                  ",{}]],"25":[["12M     sbin                                                                                                 ",{}]]}}],[0.025472,{"lines":{"0":[["8,0K    backupscript                                                                                         ",{}]],"1":[["9,7M    bin                                                                                                  ",{}]],"2":[["133M    boot                                                                                                 ",{}]],"3":[["4,0K    cdrom                                                                                                ",{}]],"4":[["4,0K    dev                                                                                                  ",{}]],"5":[["52M     etc                                                                                                  ",{}]],"6":[["160G    home                                                                                                 ",{}]],"7":[["0       initrd.img                                                                                           ",{}]],"8":[["0       initrd.img.old                                                                                       ",{}]],"9":[["671M    lib                                                                                                  ",{}]],"10":[["3,5M    lib32                                                                                                ",{}]],"11":[["4,0K    lib64                                                                                                ",{}]],"12":[["16K     lost+found                                                                                           ",{}]],"13":[["8,0K    media                                                                                                ",{}]],"14":[["4,0K    mnt                                                                                                  ",{}]],"15":[["345M    opt                                                                                                  ",{}]],"16":[["du: cannot access ‘proc/15799/task/15799/fd/4’: No such file or directory                                    ",{}]],"17":[["du: cannot access ‘proc/15799/task/15799/fdinfo/4’: No such file or directory                                ",{}]],"18":[["du: cannot access ‘proc/15799/fd/4’: No such file or directory                                               ",{}]],"19":[["du: cannot access ‘proc/15799/fdinfo/4’: No such file or directory                                           ",{}]],"20":[["0       proc                                                                                                 ",{}]],"21":[["748K    root                                                                                                 ",{}]],"22":[["du: cannot access ‘run/user/1000/gvfs’: Permission denied                                                    ",{}]],"23":[["4,7M    run                                                                                                  ",{}]],"24":[["12M     sbin                                                                                                 ",{}]],"25":[["4,0K    srv                                                                                                  ",{}]]}}],[0.048779,{"lines":{"0":[["9,7M    bin                                                                                                  ",{}]],"1":[["133M    boot                                                                                                 ",{}]],"2":[["4,0K    cdrom                                                                                                ",{}]],"3":[["4,0K    dev                                                                                                  ",{}]],"4":[["52M     etc                                                                                                  ",{}]],"5":[["160G    home                                                                                                 ",{}]],"6":[["0       initrd.img                                                                                           ",{}]],"7":[["0       initrd.img.old                                                                                       ",{}]],"8":[["671M    lib                                                                                                  ",{}]],"9":[["3,5M    lib32                                                                                                ",{}]],"10":[["4,0K    lib64                                                                                                ",{}]],"11":[["16K     lost+found                                                                                           ",{}]],"12":[["8,0K    media                                                                                                ",{}]],"13":[["4,0K    mnt                                                                                                  ",{}]],"14":[["345M    opt                                                                                                  ",{}]],"15":[["du: cannot access ‘proc/15799/task/15799/fd/4’: No such file or directory                                    ",{}]],"16":[["du: cannot access ‘proc/15799/task/15799/fdinfo/4’: No such file or directory                                ",{}]],"17":[["du: cannot access ‘proc/15799/fd/4’: No such file or directory                                               ",{}]],"18":[["du: cannot access ‘proc/15799/fdinfo/4’: No such file or directory                                           ",{}]],"19":[["0       proc                                                                                                 ",{}]],"20":[["748K    root                                                                                                 ",{}]],"21":[["du: cannot access ‘run/user/1000/gvfs’: Permission denied                                                    ",{}]],"22":[["4,7M    run                                                                                                  ",{}]],"23":[["12M     sbin                                                                                                 ",{}]],"24":[["4,0K    srv                                                                                                  ",{}]],"25":[["0       sys                                                                                                  ",{}]]}}],[0.000171,{"lines":{"0":[["133M    boot                                                                                                 ",{}]],"1":[["4,0K    cdrom                                                                                                ",{}]],"2":[["4,0K    dev                                                                                                  ",{}]],"3":[["52M     etc                                                                                                  ",{}]],"4":[["160G    home                                                                                                 ",{}]],"5":[["0       initrd.img                                                                                           ",{}]],"6":[["0       initrd.img.old                                                                                       ",{}]],"7":[["671M    lib                                                                                                  ",{}]],"8":[["3,5M    lib32                                                                                                ",{}]],"9":[["4,0K    lib64                                                                                                ",{}]],"10":[["16K     lost+found                                                                                           ",{}]],"11":[["8,0K    media                                                                                                ",{}]],"12":[["4,0K    mnt                                                                                                  ",{}]],"13":[["345M    opt                                                                                                  ",{}]],"14":[["du: cannot access ‘proc/15799/task/15799/fd/4’: No such file or directory                                    ",{}]],"15":[["du: cannot access ‘proc/15799/task/15799/fdinfo/4’: No such file or directory                                ",{}]],"16":[["du: cannot access ‘proc/15799/fd/4’: No such file or directory                                               ",{}]],"17":[["du: cannot access ‘proc/15799/fdinfo/4’: No such file or directory                                           ",{}]],"18":[["0       proc                                                                                                 ",{}]],"19":[["748K    root                                                                                                 ",{}]],"20":[["du: cannot access ‘run/user/1000/gvfs’: Permission denied                                                    ",{}]],"21":[["4,7M    run                                                                                                  ",{}]],"22":[["12M     sbin                                                                                                 ",{}]],"23":[["4,0K    srv                                                                                                  ",{}]],"24":[["0       sys                                                                                                  ",{}]],"25":[["152K    tmp                                                                                                  ",{}]]}}],[7.162563,{"lines":{"26":[["^C                                                                                                           ",{}]]},"cursor":{"x":2}}],[0.00893,{"lines":{"26":[["^Cikhsan@M5-X:/$                                                                                             ",{}]]},"cursor":{"x":17}}],[0.443451,{"lines":{"0":[["4,0K    cdrom                                                                                                ",{}]],"1":[["4,0K    dev                                                                                                  ",{}]],"2":[["52M     etc                                                                                                  ",{}]],"3":[["160G    home                                                                                                 ",{}]],"4":[["0       initrd.img                                                                                           ",{}]],"5":[["0       initrd.img.old                                                                                       ",{}]],"6":[["671M    lib                                                                                                  ",{}]],"7":[["3,5M    lib32                                                                                                ",{}]],"8":[["4,0K    lib64                                                                                                ",{}]],"9":[["16K     lost+found                                                                                           ",{}]],"10":[["8,0K    media                                                                                                ",{}]],"11":[["4,0K    mnt                                                                                                  ",{}]],"12":[["345M    opt                                                                                                  ",{}]],"13":[["du: cannot access ‘proc/15799/task/15799/fd/4’: No such file or directory                                    ",{}]],"14":[["du: cannot access ‘proc/15799/task/15799/fdinfo/4’: No such file or directory                                ",{}]],"15":[["du: cannot access ‘proc/15799/fd/4’: No such file or directory                                               ",{}]],"16":[["du: cannot access ‘proc/15799/fdinfo/4’: No such file or directory                                           ",{}]],"17":[["0       proc                                                                                                 ",{}]],"18":[["748K    root                                                                                                 ",{}]],"19":[["du: cannot access ‘run/user/1000/gvfs’: Permission denied                                                    ",{}]],"20":[["4,7M    run                                                                                                  ",{}]],"21":[["12M     sbin                                                                                                 ",{}]],"22":[["4,0K    srv                                                                                                  ",{}]],"23":[["0       sys                                                                                                  ",{}]],"24":[["152K    tmp                                                                                                  ",{}]],"25":[["^Cikhsan@M5-X:/$ ^C                                                                                          ",{}]],"26":[["ikhsan@M5-X:/$                                                                                               ",{}]]},"cursor":{"x":15}}],[0.975664,{"lines":{"26":[["ikhsan@M5-X:/$ e                                                                                             ",{}]]},"cursor":{"x":16}}],[0.211983,{"lines":{"26":[["ikhsan@M5-X:/$ ex                                                                                            ",{}]]},"cursor":{"x":17}}],[0.308819,{"lines":{"26":[["ikhsan@M5-X:/$ exi                                                                                           ",{}]]},"cursor":{"x":18}}],[0.176016,{"lines":{"26":[["ikhsan@M5-X:/$ exit                                                                                          ",{}]]},"cursor":{"x":19}}],[0.411784,{"lines":{"0":[["52M     etc                                                                                                  ",{}]],"1":[["160G    home                                                                                                 ",{}]],"2":[["0       initrd.img                                                                                           ",{}]],"3":[["0       initrd.img.old                                                                                       ",{}]],"4":[["671M    lib                                                                                                  ",{}]],"5":[["3,5M    lib32                                                                                                ",{}]],"6":[["4,0K    lib64                                                                                                ",{}]],"7":[["16K     lost+found                                                                                           ",{}]],"8":[["8,0K    media                                                                                                ",{}]],"9":[["4,0K    mnt                                                                                                  ",{}]],"10":[["345M    opt                                                                                                  ",{}]],"11":[["du: cannot access ‘proc/15799/task/15799/fd/4’: No such file or directory                                    ",{}]],"12":[["du: cannot access ‘proc/15799/task/15799/fdinfo/4’: No such file or directory                                ",{}]],"13":[["du: cannot access ‘proc/15799/fd/4’: No such file or directory                                               ",{}]],"14":[["du: cannot access ‘proc/15799/fdinfo/4’: No such file or directory                                           ",{}]],"15":[["0       proc                                                                                                 ",{}]],"16":[["748K    root                                                                                                 ",{}]],"17":[["du: cannot access ‘run/user/1000/gvfs’: Permission denied                                                    ",{}]],"18":[["4,7M    run                                                                                                  ",{}]],"19":[["12M     sbin                                                                                                 ",{}]],"20":[["4,0K    srv                                                                                                  ",{}]],"21":[["0       sys                                                                                                  ",{}]],"22":[["152K    tmp                                                                                                  ",{}]],"23":[["^Cikhsan@M5-X:/$ ^C                                                                                          ",{}]],"24":[["ikhsan@M5-X:/$ exit                                                                                          ",{}]],"25":[["exit                                                                                                         ",{}]],"26":[["                                                                                                             ",{}]]},"cursor":{"x":0}}]]